cocoai/__init__.py
cocoai/api.py
cocoai/main.py
cocoai-0.1.4.dist-info/LICENSE
cocoai-0.1.4.dist-info/METADATA
cocoai-0.1.4.dist-info/WHEEL
cocoai-0.1.4.dist-info/entry_points.txt
cocoai-0.1.4.dist-info/RECORD
