Metadata-Version: 2.1
Name: cocoai
Version: 0.1.4
Summary: Instant answers to your CLI questions in the CLI of your choice.
Home-page: https://github.com/dvlpjrs/coco
License: MIT
Author: dvlpjrs
Author-email: jrs@dvlpjrs.me
Requires-Python: >=3.8,<4.0
Classifier: License :: OSI Approved :: MIT License
Classifier: Programming Language :: Python :: 3
Classifier: Programming Language :: Python :: 3.8
Classifier: Programming Language :: Python :: 3.9
Classifier: Programming Language :: Python :: 3.10
Classifier: Programming Language :: Python :: 3.11
Requires-Dist: appdirs (>=1.4.4,<2.0.0)
Requires-Dist: click (>=8.1.7,<9.0.0)
Requires-Dist: inquirerpy (>=0.3.4,<0.4.0)
Requires-Dist: openai (>=0.28.1,<0.29.0)
Requires-Dist: pyperclip (>=1.8.2,<2.0.0)
Project-URL: Repository, https://github.com/dvlpjrs/coco
